DiamondPricePredictor/__init__.py
DiamondPricePredictor/exception.py
DiamondPricePredictor/logger.py
DiamondPricePredictor/components/__init__.py
DiamondPricePredictor/components/data_ingestion.py
DiamondPricePredictor/components/data_model_train.py
DiamondPricePredictor/config/__init__.py
DiamondPricePredictor/config/configuration.py
DiamondPricePredictor/constants/__init__.py
DiamondPricePredictor/entity/__init__.py
DiamondPricePredictor/entity/config_entity.py
DiamondPricePredictor/pipeline/__init__.py
DiamondPricePredictor/pipeline/stage_01_data_ingestion.py
DiamondPricePredictor/pipeline/stage_02_data_transofrm_model.py
DiamondPricePredictor/utils/MLUtils.py
DiamondPricePredictor/utils/__init__.py
DiamondPricePredictor/utils/common.py
Dimond_Price_Prediction-0.0.3.dist-info/LICENSE
Dimond_Price_Prediction-0.0.3.dist-info/METADATA
Dimond_Price_Prediction-0.0.3.dist-info/WHEEL
Dimond_Price_Prediction-0.0.3.dist-info/top_level.txt
Dimond_Price_Prediction-0.0.3.dist-info/RECORD
